jpyttm/__init__.py
jpyttm/calendar.py
jpyttm/constants.py
jpyttm/currencies.py
jpyttm/quotes.py
jpyttm-0.1.1.dist-info/LICENSE
jpyttm-0.1.1.dist-info/WHEEL
jpyttm-0.1.1.dist-info/METADATA
jpyttm-0.1.1.dist-info/RECORD
