Metadata-Version: 2.1
Name: jpyttm
Version: 0.1.1
Summary: Historical JPY TTM rates
Home-page: https://github.com/globophobe/jpyttm
License: MIT
Keywords: historical,jpy,ttm
Author: Alex
Author-email: globophobe@gmail.com
Requires-Python: >=3.8
Classifier: License :: OSI Approved :: MIT License
Classifier: Operating System :: OS Independent
Classifier: Programming Language :: Python :: 3
Classifier: Programming Language :: Python :: 3.10
Classifier: Programming Language :: Python :: 3.8
Classifier: Programming Language :: Python :: 3.9
Requires-Dist: beautifulsoup4
Requires-Dist: lxml
Requires-Dist: pytz
Requires-Dist: requests
Project-URL: Repository, https://github.com/globophobe/jpyttm
